LICENSE
option/__init__.py
option/option_.py
option/py.typed
option/result.py
option/types_.py
option-2.0.1.dist-info/LICENSE
option-2.0.1.dist-info/WHEEL
option-2.0.1.dist-info/METADATA
option-2.0.1.dist-info/RECORD
