Metadata-Version: 2.1
Name: option
Version: 2.0.1
Summary: Rust like Option and Result types in Python
Home-page: https://mat1g3r.github.io/option/
License: MIT
Author: Peijun Ma
Author-email: peijun.ma@protonmail.com
Requires-Python: >=3.7,<4
Classifier: Development Status :: 5 - Production/Stable
Classifier: Intended Audience :: Developers
Classifier: License :: OSI Approved :: MIT License
Classifier: Programming Language :: Python :: 3
Classifier: Programming Language :: Python :: 3.10
Classifier: Programming Language :: Python :: 3.7
Classifier: Programming Language :: Python :: 3.8
Classifier: Programming Language :: Python :: 3.9
Classifier: Topic :: Software Development :: Libraries
Project-URL: Repository, https://github.com/MaT1g3R/option
